MANIFEST.in
README.md
setup.py
ChiSquareSaranya/__init__.py
ChiSquareSaranya/chipyfunction01.py
ChiSquareSaranya.egg-info/PKG-INFO
ChiSquareSaranya.egg-info/SOURCES.txt
ChiSquareSaranya.egg-info/dependency_links.txt
ChiSquareSaranya.egg-info/top_level.txt